<?xml version="1.0" encoding="utf-8" ?>

<Defs>

	<!-- orb of conviction -->  
	
	  <TorannMagic.TMAbilityDef ParentName="BaseMagicAbility">
        <defName>TM_Artifact_Conviction</defName>
        <label>Conviction</label>
        <uiIconPath>UI/orb_conviction</uiIconPath>
		<manaCost>1.05</manaCost>
        <description>Overpower a pawn with conviction to join your cause. This power will exact a heavy toll on the caster.
		
Use of Conviction will destroy the orb.</description>
		<MainVerb Class="AbilityUser.VerbProperties_Ability">
            <verbClass>TorannMagic.Enchantment.Verb_OrbTraitor</verbClass>
				<tooltipShowProjectileDamage>false</tooltipShowProjectileDamage>
				<tooltipShowExtraDamages>false</tooltipShowExtraDamages>
				<tooltipShowHediffsToApply>false</tooltipShowHediffsToApply>
				<tooltipShowMentalStatesToApply>false</tooltipShowMentalStatesToApply>
            <hasStandardCommand>true</hasStandardCommand>
            <defaultProjectile>Projectile_Default</defaultProjectile>
            <abilityDef>TM_Artifact_Conviction</abilityDef>
            <warmupTime>2</warmupTime>
            <SecondsToRecharge>600</SecondsToRecharge>
            <range>50</range>
            <burstShotCount>1</burstShotCount>
            <soundCast>TM_Gong</soundCast>
			<soundCastTail>GunTail_Medium</soundCastTail>
            <muzzleFlashScale>30</muzzleFlashScale>
		    <AlwaysHits>true</AlwaysHits>
            <isPrimary>true</isPrimary>
			<isViolent>false</isViolent>
			<targetParams>
                <canTargetPawns>true</canTargetPawns>
                <canTargetBuildings>false</canTargetBuildings>
                <canTargetSelf>false</canTargetSelf>
                <canTargetLocations>false</canTargetLocations>
            </targetParams>
        </MainVerb>
    </TorannMagic.TMAbilityDef>
	
	<!-- orb of souls -->  
	
	<AbilityUser.AbilityDef ParentName="BaseArtifactAbility">
        <defName>TM_Artifact_TraitThief</defName>
        <label>Devour Soul</label>
        <uiIconPath>UI/orb_souls</uiIconPath>
        <description>Steal the traits of another pawn.</description>
		<MainVerb Class="AbilityUser.VerbProperties_Ability">
            <verbClass>TorannMagic.Enchantment.Verb_OrbTraitThief</verbClass>
				<tooltipShowProjectileDamage>false</tooltipShowProjectileDamage>
				<tooltipShowExtraDamages>false</tooltipShowExtraDamages>
				<tooltipShowHediffsToApply>false</tooltipShowHediffsToApply>
				<tooltipShowMentalStatesToApply>false</tooltipShowMentalStatesToApply>
            <hasStandardCommand>true</hasStandardCommand>
            <defaultProjectile>Projectile_Default</defaultProjectile>
            <abilityDef>TM_Artifact_TraitThief</abilityDef>
            <warmupTime>10</warmupTime>
            <SecondsToRecharge>600</SecondsToRecharge>
            <range>20</range>
            <burstShotCount>1</burstShotCount>
            <soundCast>TM_Gong</soundCast>
			<soundCastTail>GunTail_Medium</soundCastTail>
            <muzzleFlashScale>10</muzzleFlashScale>
		    <AlwaysHits>true</AlwaysHits>
            <isPrimary>true</isPrimary>
			<isViolent>true</isViolent>
			<targetParams>
                <canTargetPawns>true</canTargetPawns>
                <canTargetBuildings>false</canTargetBuildings>
                <canTargetSelf>false</canTargetSelf>
                <canTargetLocations>false</canTargetLocations>
            </targetParams>
        </MainVerb>
    </AbilityUser.AbilityDef>
	
	<AbilityUser.AbilityDef ParentName="BaseArtifactAbility">
        <defName>TM_Artifact_TraitInfuse</defName>
        <label>Infuse Soul</label>
        <uiIconPath>UI/orb_souls_full</uiIconPath>
        <description>Infuse sealed traits into a human-like pawn.</description>
		<MainVerb Class="AbilityUser.VerbProperties_Ability">
            <verbClass>TorannMagic.Enchantment.Verb_OrbTraitInfuse</verbClass>
				<tooltipShowProjectileDamage>false</tooltipShowProjectileDamage>
				<tooltipShowExtraDamages>false</tooltipShowExtraDamages>
				<tooltipShowHediffsToApply>false</tooltipShowHediffsToApply>
				<tooltipShowMentalStatesToApply>false</tooltipShowMentalStatesToApply>
            <hasStandardCommand>true</hasStandardCommand>
            <defaultProjectile>Projectile_Default</defaultProjectile>
            <abilityDef>TM_Artifact_TraitInfuse</abilityDef>
            <warmupTime>5</warmupTime>
            <SecondsToRecharge>600</SecondsToRecharge>
            <range>20</range>
            <burstShotCount>1</burstShotCount>
            <soundCast>TM_Gong</soundCast>
			<soundCastTail>GunTail_Medium</soundCastTail>
            <muzzleFlashScale>10</muzzleFlashScale>
		    <AlwaysHits>true</AlwaysHits>
            <isPrimary>true</isPrimary>
			<isViolent>false</isViolent>
			<targetParams>
                <canTargetPawns>true</canTargetPawns>
                <canTargetBuildings>false</canTargetBuildings>
                <canTargetSelf>true</canTargetSelf>
                <canTargetLocations>false</canTargetLocations>
            </targetParams>
        </MainVerb>
    </AbilityUser.AbilityDef>
	
	<!-- winter's reign -->
	
	<TorannMagic.TMAbilityDef ParentName="BaseArtifactAbility">
        <defName>TM_Weapon_WintersFury</defName>
        <label>Winter's Fury</label>
        <uiIconPath>UI/wintersfury</uiIconPath>
        <description>Covers the map in rolling waves of dark, angry clouds carrying winters' biting scorn.</description>        
		<MainVerb Class="AbilityUser.VerbProperties_Ability">
            <verbClass>TorannMagic.Enchantment.Verb_WeaponWintersFury</verbClass>
            <hasStandardCommand>true</hasStandardCommand>
            <defaultProjectile>Projectile_Default</defaultProjectile>
            <abilityDef>TM_Weapon_WintersFury</abilityDef>
            <AbilityTargetCategory>TargetSelf</AbilityTargetCategory>
            <targetParams>
			  <canTargetPawns>true</canTargetPawns>
			  <canTargetBuildings>false</canTargetBuildings>
			  <canTargetSelf>true</canTargetSelf>
			  <canTargetLocations>false</canTargetLocations>
			</targetParams>
            <warmupTime>5</warmupTime>
            <SecondsToRecharge>600000</SecondsToRecharge>
            <range>0</range>
			<isViolent>false</isViolent>
            <burstShotCount>1</burstShotCount>
            <ticksBetweenBurstShots>1</ticksBetweenBurstShots>
            <soundCast>Message_PositiveEvent</soundCast>
            <muzzleFlashScale>0</muzzleFlashScale>
            <isPrimary>false</isPrimary>
        </MainVerb>
    </TorannMagic.TMAbilityDef>

</Defs>
